fabs/__init__.py
fabs/brun.py
fabs/bstore.py
fabs/cmd.py
fabs/config.py
fabs/const.py
fabs/db.py
fabs/dumpjob.py
fabs/err.py
fabs/log.py
fabs/log_cli.conf
fabs/log_daemon.conf
fabs/path.py
fabs/report.py
fabs/restore.py
fabs/server.py
fabs/testutil.py
fabs/util.py
fabs/voldump.py
fabs/scripts/__init__.py
fabs/scripts/base.py
fabs/scripts/fabsys.py
fabs/scripts/sbaf.py
fabs-1.1.data/data/share/man/man1/fabsys.1
fabs-1.1.data/data/share/man/man1/fabsys_backup-inject.1
fabs-1.1.data/data/share/man/man1/fabsys_backup-kill.1
fabs-1.1.data/data/share/man/man1/fabsys_backup-needed.1
fabs-1.1.data/data/share/man/man1/fabsys_backup-retry.1
fabs-1.1.data/data/share/man/man1/fabsys_backup-start.1
fabs-1.1.data/data/share/man/man1/fabsys_backup-status.1
fabs-1.1.data/data/share/man/man1/fabsys_config.1
fabs-1.1.data/data/share/man/man1/fabsys_db-clean.1
fabs-1.1.data/data/share/man/man1/fabsys_db-init.1
fabs-1.1.data/data/share/man/man1/fabsys_db-upgrade.1
fabs-1.1.data/data/share/man/man1/fabsys_dump-delete.1
fabs-1.1.data/data/share/man/man1/fabsys_dump-find.1
fabs-1.1.data/data/share/man/man1/fabsys_dump-list.1
fabs-1.1.data/data/share/man/man1/fabsys_restore-kill.1
fabs-1.1.data/data/share/man/man1/fabsys_restore-retry.1
fabs-1.1.data/data/share/man/man1/fabsys_restore-start.1
fabs-1.1.data/data/share/man/man1/fabsys_restore-status.1
fabs-1.1.data/data/share/man/man1/fabsys_server.1
fabs-1.1.data/data/share/man/man1/fabsys_storage-init.1
fabs-1.1.data/data/share/man/man1/fabsys_storage-trim.1
fabs-1.1.data/data/share/man/man1/sbaf.1
fabs-1.1.dist-info/LICENSE
fabs-1.1.dist-info/METADATA
fabs-1.1.dist-info/WHEEL
fabs-1.1.dist-info/entry_points.txt
fabs-1.1.dist-info/top_level.txt
fabs-1.1.dist-info/RECORD
