Metadata-Version: 2.1
Name: fabs
Version: 1.1
Summary: A flexible backup suite for AFS cells
Home-page: https://github.com/openafs-contrib/fabs
Author: Sine Nomine Associates
Author-email: sna-packager@sinenomine.net
License: ISC
License-File: LICENSE
Requires-Dist: PyYAML (>=3.10)
Requires-Dist: SQLAlchemy (>=0.8)
Requires-Dist: python-dateutil
Provides-Extra: alembic
Requires-Dist: Alembic (>=0.4) ; extra == 'alembic'
